{"65184":{"channel":"nTG8t5ztNKaRfQNhnqeZgrIhNPN8RUVwdMAB9kik","start":"1669937400","end":"1669940280","first":"B","idtitle":"BIGCATWEEK","title":"Big Cat Week","program_id":"J9ZwfW3AvRIqYvuL4y7qMSFW5pjcFE71RgOyVYR-","date":"","icon":"https:\/\/m7be2.solocoo.tv\/m7be2iphone\/mmchan\/mpimages\/260x145\/sihoxHf9oewq6Fw0n5SOTQ.jpg","description":"","category":""},"65185":{"channel":"nTG8t5ztNKaRfQNhnqeZgrIhNPN8RUVwdMAB9kik","start":"1669940280","end":"1669943160","first":"W","idtitle":"WHENSHARKSATTACKCHAOSINCALIFORNIA","title":"When Sharks Attack : Chaos In California","program_id":"Juo23odUZQSs_DInrRyh3UAflELX3vRQIKWq-M1v","date":"","icon":"https:\/\/m7be2.solocoo.tv\/m7be2iphone\/mmchan\/mpimages\/260x145\/qKSMQRssaY2rSrE83PGuIg.jpg","description":"","category":""},"65186":{"channel":"nTG8t5ztNKaRfQNhnqeZgrIhNPN8RUVwdMAB9kik","start":"1669943160","end":"1669946040","first":"S","idtitle":"SNAKESINTHECITYTENFOOTMAMBA","title":"Snakes in the City : Ten Foot Mamba","program_id":"9DCWrlV-3Er0v1GkaN9fK56-dk1XhQPhFXoJ4xA4","date":"","icon":"https:\/\/m7be2.solocoo.tv\/m7be2iphone\/mmchan\/mpimages\/260x145\/x8XQmQiI-2pVw2jnUrHsaA.jpg","description":"","category":""},"65187":{"channel":"nTG8t5ztNKaRfQNhnqeZgrIhNPN8RUVwdMAB9kik","start":"1669946040","end":"1669948800","first":"A","idtitle":"AMERICASFUNNIESTHOMEVIDEOSANIMALEDITIONPAWORDER","title":"America's Funniest Home Videos: Animal Edition : Paw & Order","program_id":"HhdY6qVS9gE0WrKB5cvJnYMxY6IBSFxcVHe0Vqfx","date":"","icon":"https:\/\/m7be2.solocoo.tv\/m7be2iphone\/mmchan\/mpimages\/260x145\/gGc1uneMNKOYSFaaYXf4Kw.jpg","description":"","category":""},"65188":{"channel":"nTG8t5ztNKaRfQNhnqeZgrIhNPN8RUVwdMAB9kik","start":"1669948800","end":"1669951740","first":"A","idtitle":"AMERICASFUNNIESTHOMEVIDEOSANIMALEDITIONSCAREDCAT","title":"America's Funniest Home Videos: Animal Edition : Scared Cat","program_id":"4TzX9hBoEW7YJAWMaVP_RgGNZOxnwhjcnWLLbyMy","date":"","icon":"https:\/\/m7be2.solocoo.tv\/m7be2iphone\/mmchan\/mpimages\/260x145\/K4z4x89ZeB6IRlYh1TYABg.jpg","description":"","category":""},"65189":{"channel":"nTG8t5ztNKaRfQNhnqeZgrIhNPN8RUVwdMAB9kik","start":"1669951740","end":"1669954620","first":"W","idtitle":"WHENSHARKSATTACKCHAOSINCALIFORNIA","title":"When Sharks Attack : Chaos In California","program_id":"O8N3TK6n_79Nhk0hCqtesGYktmv-92aBIccoxf0h","date":"","icon":"https:\/\/m7be2.solocoo.tv\/m7be2iphone\/mmchan\/mpimages\/260x145\/qKSMQRssaY2rSrE83PGuIg.jpg","description":"","category":""},"65190":{"channel":"nTG8t5ztNKaRfQNhnqeZgrIhNPN8RUVwdMAB9kik","start":"1669954620","end":"1669957200","first":"S","idtitle":"SNAKESINTHECITYTENFOOTMAMBA","title":"Snakes in the City : Ten Foot Mamba","program_id":"qeWfTsYJ-N1vE7EdCbneJ--g6qXoaeD2nC-DG8Qs","date":"","icon":"https:\/\/m7be2.solocoo.tv\/m7be2iphone\/mmchan\/mpimages\/260x145\/x8XQmQiI-2pVw2jnUrHsaA.jpg","description":"","category":""},"65191":{"channel":"nTG8t5ztNKaRfQNhnqeZgrIhNPN8RUVwdMAB9kik","start":"1669957200","end":"1669958700","first":"A","idtitle":"AMERICASWILDSPACESDEEPINTOTHEGRANDCANYON","title":"America's Wild Spaces : Deep Into the Grand Canyon","program_id":"cksgdWWOSlG_fJPJ-Dd3T72v6D4fbwALxJ21EdgU","date":"","icon":"https:\/\/m7be2.solocoo.tv\/m7be2iphone\/mmchan\/mpimages\/260x145\/pdzx51BfWYshl8BGEyP-fA.jpg","description":"National Geographic sluit zich aan bij een zeldzame missie om de volledige 445 kilometer van de Grand Canyon te verkennen en de mysteries te onderzoeken.","category":""},"65192":{"channel":"nTG8t5ztNKaRfQNhnqeZgrIhNPN8RUVwdMAB9kik","start":"1669958700","end":"1669960200","first":"A","idtitle":"AMERICASWILDSPACESMYSTERIESOFDEATHVALLEY","title":"America's Wild Spaces : Mysteries of Death Valley","program_id":"NI1GSYUvqtRgp60bDJDd29cIfbvKWWv8cbkfFZcz","date":"","icon":"https:\/\/m7be2.solocoo.tv\/m7be2iphone\/mmchan\/mpimages\/260x145\/RzTo2OaGaKHi_epzeesBmQ.jpg","description":"Reis mee met JT Reynolds, onderzoeker in Death Valley, en ontmoet de wetenschappers die deze wilde plek beschermen.","category":""},"65193":{"channel":"nTG8t5ztNKaRfQNhnqeZgrIhNPN8RUVwdMAB9kik","start":"1669960200","end":"1669963080","first":"W","idtitle":"WHENSHARKSATTACKCAROLINADREAD","title":"When Sharks Attack : Carolina Dread","program_id":"34aK224RtryO-r3DfKT_WoPHUhNxoS5rUp_JvPa_","date":"","icon":"https:\/\/m7be2.solocoo.tv\/m7be2iphone\/mmchan\/mpimages\/260x145\/Xl4HeklUfOQjMTWvntJd4w.jpg","description":"","category":""},"65194":{"channel":"nTG8t5ztNKaRfQNhnqeZgrIhNPN8RUVwdMAB9kik","start":"1669963080","end":"1669965960","first":"A","idtitle":"AFRICASDEADLIESTYOUNGBLOOD","title":"Africa's Deadliest : Young Blood","program_id":"7yC5c2pfGOGhPLYCwEORkMzzGDJBpVRcsk80eB5O","date":"","icon":"https:\/\/m7be2.solocoo.tv\/m7be2iphone\/mmchan\/mpimages\/260x145\/LrdsjoKZmZjf_ZuRQH0mHg.jpg","description":"","category":""},"65195":{"channel":"nTG8t5ztNKaRfQNhnqeZgrIhNPN8RUVwdMAB9kik","start":"1669965960","end":"1669968960","first":"L","idtitle":"LAKETANGANYIKAAFRICASBLUEHEART","title":"Lake Tanganyika: Africa's Blue Heart","program_id":"NFksTW_s0pxvTFB_GRWRlQ_sfAceUDwKaOKlGXp9","date":"","icon":"https:\/\/m7be2.solocoo.tv\/m7be2iphone\/mmchan\/mpimages\/260x145\/a-63kH4vwt-LYbuzmZ0FFA.jpg","description":"","category":""},"65196":{"channel":"nTG8t5ztNKaRfQNhnqeZgrIhNPN8RUVwdMAB9kik","start":"1669968960","end":"1669971900","first":"R","idtitle":"RELENTLESSENEMIES","title":"Relentless Enemies","program_id":"0XbLCJcsD0EYKAtPKX0wEtHq9OGOx7O4RWXMpYW0","date":"","icon":"https:\/\/m7be2.solocoo.tv\/m7be2iphone\/mmchan\/mpimages\/260x145\/6TMwL_5vErES5cyWig4e7A.jpg","description":"Een kudde bizons moet het leefgebied van leeuwen door en wordt bedreigd door overstromingen in de Okavango. Het verhaal van deze dieren komt vanuit de thuisbasis van de Jouberts in Botswana.","category":""},"65197":{"channel":"nTG8t5ztNKaRfQNhnqeZgrIhNPN8RUVwdMAB9kik","start":"1669971900","end":"1669974780","first":"W","idtitle":"WHENSHARKSATTACKCAROLINADREAD","title":"When Sharks Attack : Carolina Dread","program_id":"JRpCZ5IE0bMEUa4NAziHWxnpt0WWI49nKqTCvSs3","date":"","icon":"https:\/\/m7be2.solocoo.tv\/m7be2iphone\/mmchan\/mpimages\/260x145\/Xl4HeklUfOQjMTWvntJd4w.jpg","description":"Programmabeschrijving niet beschikbaar","category":""},"65198":{"channel":"nTG8t5ztNKaRfQNhnqeZgrIhNPN8RUVwdMAB9kik","start":"1669974780","end":"1669977720","first":"A","idtitle":"AFRICASDEADLIESTYOUNGBLOOD","title":"Africa's Deadliest : Young Blood","program_id":"LgogRL0nl8ENVnhnMGhZkfRzouxZE_AJ5xYq9f1F","date":"","icon":"https:\/\/m7be2.solocoo.tv\/m7be2iphone\/mmchan\/mpimages\/260x145\/LrdsjoKZmZjf_ZuRQH0mHg.jpg","description":"Voor roofdieren en prooi is het doden of gedood worden. Vanaf hun geboorte moeten ze vechten om te overleven.","category":""},"65199":{"channel":"nTG8t5ztNKaRfQNhnqeZgrIhNPN8RUVwdMAB9kik","start":"1669977720","end":"1669980360","first":"S","idtitle":"SNAKESINTHECITYMAMBAINMYCLOSET","title":"Snakes in the City : Mamba in My Closet!","program_id":"qk-CqfDZ0n7KzRJPl1THZ_3-wn59stYc_EKBWgKc","date":"","icon":"https:\/\/m7be2.solocoo.tv\/m7be2iphone\/mmchan\/mpimages\/260x145\/1hZSyscQ20LfxgzyODbxyQ.jpg","description":"Het is slangenseizoen in Durban. Elke zomer reizen slangenvangers Simon en Siouxsie door de stad om angstige inwoners te helpen.","category":""},"65200":{"channel":"nTG8t5ztNKaRfQNhnqeZgrIhNPN8RUVwdMAB9kik","start":"1669980360","end":"1669983420","first":"L","idtitle":"LAKETANGANYIKAAFRICASBLUEHEART","title":"Lake Tanganyika: Africa's Blue Heart","program_id":"51w-bPlvUYnvA1u0zkGtmHIFDP-vKUaM5QFnwlnd","date":"","icon":"https:\/\/m7be2.solocoo.tv\/m7be2iphone\/mmchan\/mpimages\/260x145\/a-63kH4vwt-LYbuzmZ0FFA.jpg","description":"Programmabeschrijving niet beschikbaar","category":""},"65201":{"channel":"nTG8t5ztNKaRfQNhnqeZgrIhNPN8RUVwdMAB9kik","start":"1669983420","end":"1669986240","first":"Z","idtitle":"ZEBSBIGFISHGIANTGOONCHGREATWHITESTURGEON","title":"Zeb's Big Fish: Giant Goonch : Great White Sturgeon","program_id":"Nl-gSfds4zR8xmWCy_Df98WG_xqKpaYcJYVouLNT","date":"","icon":"https:\/\/m7be2.solocoo.tv\/m7be2iphone\/mmchan\/mpimages\/260x145\/4mFwTq-o60s_s5JbTBs9bQ.jpg","description":"","category":""},"65202":{"channel":"nTG8t5ztNKaRfQNhnqeZgrIhNPN8RUVwdMAB9kik","start":"1669986240","end":"1669989060","first":"Z","idtitle":"ZEBSBIGFISHGIANTGOONCHGIANTSTINGRAY","title":"Zeb's Big Fish: Giant Goonch : Giant Stingray","program_id":"3v9IbNERuk8OTlSeCujHnJsbresE42BrfGJIvrov","date":"","icon":"https:\/\/m7be2.solocoo.tv\/m7be2iphone\/mmchan\/mpimages\/260x145\/MWjzSAplHP4qPEFIBR4XzA.jpg","description":"","category":""},"65203":{"channel":"nTG8t5ztNKaRfQNhnqeZgrIhNPN8RUVwdMAB9kik","start":"1669989060","end":"1669991820","first":"R","idtitle":"RELENTLESSENEMIES","title":"Relentless Enemies","program_id":"V5QJB8JWe-9j0WepVVrnwWZbQJo0wuLFqzCbye7C","date":"","icon":"https:\/\/m7be2.solocoo.tv\/m7be2iphone\/mmchan\/mpimages\/260x145\/6TMwL_5vErES5cyWig4e7A.jpg","description":"Een kudde bizons moet het leefgebied van leeuwen door en wordt bedreigd door overstromingen in de Okavango. Het verhaal van deze dieren komt vanuit de thuisbasis van de Jouberts in Botswana.","category":""},"65204":{"channel":"nTG8t5ztNKaRfQNhnqeZgrIhNPN8RUVwdMAB9kik","start":"1669991820","end":"1669994640","first":"A","idtitle":"AFRICASDEADLIESTKILLERSOFTHEDEEP","title":"Africa's Deadliest : Killers of the Deep","program_id":"R1ChQiONgiSpXFgSFLwUf1zd68wc_9g59ZIwN7Wc","date":"","icon":"https:\/\/m7be2.solocoo.tv\/m7be2iphone\/mmchan\/mpimages\/260x145\/DmGK-EBsVx2-IIQkdczw4Q.jpg","description":"Programmabeschrijving niet beschikbaar","category":""},"65205":{"channel":"nTG8t5ztNKaRfQNhnqeZgrIhNPN8RUVwdMAB9kik","start":"1669994640","end":"1669997460","first":"T","idtitle":"THEINCREDIBLEDRPOLPOLNADOWARNING","title":"The Incredible Dr Pol : Polnado Warning","program_id":"KjEW-FxQuDL2YRmQUw6HAu5UpYMOI5aP_FsYzo7p","date":"","icon":"https:\/\/m7be2.solocoo.tv\/m7be2iphone\/mmchan\/mpimages\/260x145\/kzdjabuBEazKb_KKqwFc9A.jpg","description":"","category":""},"65206":{"channel":"nTG8t5ztNKaRfQNhnqeZgrIhNPN8RUVwdMAB9kik","start":"1669997460","end":"1670000400","first":"W","idtitle":"WORLDSDEADLIEST7DEADLYSINS","title":"World's Deadliest : 7 Deadly Sins","program_id":"Ip6zT50YbmfGKkXTXBb1ZIb0M6hRQYPdpmpFBadf","date":"","icon":"https:\/\/m7be2.solocoo.tv\/m7be2iphone\/mmchan\/mpimages\/260x145\/6sYmYowUeAAN1Phzdtn66w.jpg","description":"Sommige dieren hebben vlijmscherpe tanden waarmee ze spieren verscheuren, terwijl anderen hun gif rechtstreeks in je aderen kunnen spuiten.","category":""},"65207":{"channel":"nTG8t5ztNKaRfQNhnqeZgrIhNPN8RUVwdMAB9kik","start":"1670000400","end":"1670003280","first":"C","idtitle":"CRITTERFIXERSCOUNTRYVETSLUCKYDUCKY","title":"Critter Fixers: Country Vets : Lucky Ducky","program_id":"-ByAFhZfXrnLAIn0YmrLYMQxwN2lbjbCAFSd9b5g","date":"","icon":"https:\/\/m7be2.solocoo.tv\/m7be2iphone\/mmchan\/mpimages\/260x145\/uB7OQtlK7t4qGV5a_xKfMg.jpg","description":"Programmabeschrijving niet beschikbaar","category":""},"65208":{"channel":"nTG8t5ztNKaRfQNhnqeZgrIhNPN8RUVwdMAB9kik","start":"1670003280","end":"1670006220","first":"L","idtitle":"LAKETANGANYIKAAFRICASBLUEHEART","title":"Lake Tanganyika: Africa's Blue Heart","program_id":"umI2BasLxVgxmzZtkQNALKFojG9iRzw1atWauleX","date":"","icon":"https:\/\/m7be2.solocoo.tv\/m7be2iphone\/mmchan\/mpimages\/260x145\/a-63kH4vwt-LYbuzmZ0FFA.jpg","description":"","category":""},"65209":{"channel":"nTG8t5ztNKaRfQNhnqeZgrIhNPN8RUVwdMAB9kik","start":"1670006220","end":"1670009160","first":"A","idtitle":"AFRICASDEADLIESTKILLERSOFTHEDEEP","title":"Africa's Deadliest : Killers of the Deep","program_id":"JcgJpZKqUcr_LJpXcFAnFH_mVSRdG19lvb5oZUKS","date":"","icon":"https:\/\/m7be2.solocoo.tv\/m7be2iphone\/mmchan\/mpimages\/260x145\/DmGK-EBsVx2-IIQkdczw4Q.jpg","description":"","category":""},"65210":{"channel":"nTG8t5ztNKaRfQNhnqeZgrIhNPN8RUVwdMAB9kik","start":"1670009160","end":"1670012100","first":"C","idtitle":"CRITTERFIXERSCOUNTRYVETSLUCKYDUCKY","title":"Critter Fixers: Country Vets : Lucky Ducky","program_id":"IMpCffaPR9WH4X4WSZvalVva0jfexcRdD5jSUJhT","date":"","icon":"https:\/\/m7be2.solocoo.tv\/m7be2iphone\/mmchan\/mpimages\/260x145\/uB7OQtlK7t4qGV5a_xKfMg.jpg","description":"","category":""},"65211":{"channel":"nTG8t5ztNKaRfQNhnqeZgrIhNPN8RUVwdMAB9kik","start":"1670012100","end":"1670014980","first":"T","idtitle":"THEINCREDIBLEDRPOLCOMPILATIONSDAIRYPOPPINS","title":"The Incredible Dr. Pol Compilations : Dairy Poppins","program_id":"GhyWJSqFV0FBo402LielCKIwezyEu16T1yAr64pv","date":"","icon":"https:\/\/m7be2.solocoo.tv\/m7be2iphone\/mmchan\/mpimages\/260x145\/Btc9nAE6OCv8Fr-z3ar2kw.jpg","description":"","category":""},"65212":{"channel":"nTG8t5ztNKaRfQNhnqeZgrIhNPN8RUVwdMAB9kik","start":"1670014980","end":"1670017920","first":"D","idtitle":"DRKSEXOTICANIMALERSILLYRABBIT","title":"Dr K's Exotic Animal ER : Silly Rabbit...","program_id":"PxY7b0THIfQ4zLAGu81jLf_BKyfrUb7Mwx0ef-i-","date":"","icon":"https:\/\/m7be2.solocoo.tv\/m7be2iphone\/mmchan\/mpimages\/260x145\/gdoNzC34S69JEIdoZw-7PQ.jpg","description":"","category":""},"65213":{"channel":"nTG8t5ztNKaRfQNhnqeZgrIhNPN8RUVwdMAB9kik","start":"1670017920","end":"1670020860","first":"W","idtitle":"WORLDSDEADLIEST7DEADLYSINS","title":"World's Deadliest : 7 Deadly Sins","program_id":"ZFWnsuwF8Y-jQ8QYN-yDYYpPIh3UOCORSVt1i9cY","date":"","icon":"https:\/\/m7be2.solocoo.tv\/m7be2iphone\/mmchan\/mpimages\/260x145\/6sYmYowUeAAN1Phzdtn66w.jpg","description":"","category":""},"65214":{"channel":"nTG8t5ztNKaRfQNhnqeZgrIhNPN8RUVwdMAB9kik","start":"1670020860","end":"1670023800","first":"C","idtitle":"CRITTERFIXERSCOUNTRYVETSLUCKYDUCKY","title":"Critter Fixers: Country Vets : Lucky Ducky","program_id":"w-Fc4Jmuvt7HPqKiGYY3rVC7LSDabzJePWzkHpx-","date":"","icon":"https:\/\/m7be2.solocoo.tv\/m7be2iphone\/mmchan\/mpimages\/260x145\/uB7OQtlK7t4qGV5a_xKfMg.jpg","description":"","category":""}}