{"27022":{"channel":"-9avOOhqtMF_2462C_Nxbzc5YXeNaxxVRpnb7Vlv","start":"1669357560","end":"1669360680","title":"Brad Mehldau plays the Beatles","program_id":"tCALOVRjY98Tm1Ks8gGteSJuqsWisk5EzM4-HhrJ","date":"","icon":"https:\/\/m7be2.solocoo.tv\/m7be2iphone\/mmchan\/mpimages\/208x308\/O6eDluKpnv6l9Tjck1LokA.jpg","description":"","category":""},"31548":{"channel":"-9avOOhqtMF_2462C_Nxbzc5YXeNaxxVRpnb7Vlv","start":"1669476960","end":"1669480020","title":"Brad Mehldau plays the Beatles","program_id":"C4uBk7MgIhyBIEg_Gq7lIwEuvRgcddJ8eK07kCcx","date":"","icon":"https:\/\/m7be2.solocoo.tv\/m7be2iphone\/mmchan\/mpimages\/260x145\/O6eDluKpnv6l9Tjck1LokA.jpg","description":"","category":""},"40262":{"channel":"-9avOOhqtMF_2462C_Nxbzc5YXeNaxxVRpnb7Vlv","start":"1669596300","end":"1669599420","title":"Brad Mehldau plays the Beatles","program_id":"vhdB7hB8n4zNH0tcKxHEYHS-qw-onAttg0astuA7","date":"","icon":"https:\/\/m7be2.solocoo.tv\/m7be2iphone\/mmchan\/mpimages\/260x145\/O6eDluKpnv6l9Tjck1LokA.jpg","description":"","category":""},"44777":{"channel":"-9avOOhqtMF_2462C_Nxbzc5YXeNaxxVRpnb7Vlv","start":"1669697820","end":"1669700880","title":"Brad Mehldau plays the Beatles","program_id":"lv8JN1VzQJt80HlELvj7JpuMRasMExagBnCYk1xH","date":"","icon":"https:\/\/m7be2.solocoo.tv\/m7be2iphone\/mmchan\/mpimages\/260x145\/O6eDluKpnv6l9Tjck1LokA.jpg","description":"","category":""},"49320":{"channel":"-9avOOhqtMF_2462C_Nxbzc5YXeNaxxVRpnb7Vlv","start":"1669786680","end":"1669789740","title":"Brad Mehldau plays the Beatles","program_id":"1V1GLia-lk4GHrJe4PAhqmhAPXLQ61rmKXuwuC_B","date":"","icon":"https:\/\/m7be2.solocoo.tv\/m7be2iphone\/mmchan\/mpimages\/260x145\/O6eDluKpnv6l9Tjck1LokA.jpg","description":"","category":""},"53898":{"channel":"-9avOOhqtMF_2462C_Nxbzc5YXeNaxxVRpnb7Vlv","start":"1669866600","end":"1669869660","title":"Brad Mehldau plays the Beatles","program_id":"14Aw0B-vSALz9s7Tc91FM0Yz4FEt9AXJ0tjoXTv0","date":"","icon":"https:\/\/m7be2.solocoo.tv\/m7be2iphone\/mmchan\/mpimages\/260x145\/O6eDluKpnv6l9Tjck1LokA.jpg","description":"","category":""},"58422":{"channel":"-9avOOhqtMF_2462C_Nxbzc5YXeNaxxVRpnb7Vlv","start":"1669936500","end":"1669939560","title":"Brad Mehldau plays the Beatles","program_id":"gzQcSk2jfiYROGYqJapIxrm8CxVMavgwtdfOnuyQ","date":"","icon":"https:\/\/m7be2.solocoo.tv\/m7be2iphone\/mmchan\/mpimages\/260x145\/O6eDluKpnv6l9Tjck1LokA.jpg","description":"","category":""}}