{"17892":{"channel":"-9avOOhqtMF_2462C_Nxbzc5YXeNaxxVRpnb7Vlv","start":"1669142100","end":"1669145400","title":"Daniel Barenboim plays the Piano Sonatas by Beethoven: Piano Sonata no. 29","program_id":"qwCYYls1UnMLJ2VtUIfLgPwWjF3iODf9Lb1vbDkv","date":"","icon":"https:\/\/m7be2.solocoo.tv\/m7be2iphone\/mmchan\/mpimages\/208x308\/qRKU5kQsgv2m9qPr50UPbw.jpg","description":"","category":""},"31601":{"channel":"-9avOOhqtMF_2462C_Nxbzc5YXeNaxxVRpnb7Vlv","start":"1669382640","end":"1669385760","title":"Daniel Barenboim plays the Piano Sonatas by Beethoven: Piano Sonata no. 29","program_id":"2JgP-RGM8emHk8_u2NyKOlobibcsuPMNXr1NuL15","date":"","icon":"https:\/\/m7be2.solocoo.tv\/m7be2iphone\/mmchan\/mpimages\/208x308\/vFT2kqtdy6vpN-mEIat2gQ.jpg","description":"","category":""}}