{"14995":{"channel":"G7pEDZBzf7cxmJlOght9Q9H0LyzE7DzQmTDi7OuI","start":"1669008600","end":"1669010400","title":"Sports Women","program_id":"4TcwD-OiCam7--zhhnKa3fb94iJFi66ukLjWFSw0","date":"","icon":"https:\/\/m7be2.solocoo.tv\/m7be2iphone\/mmchan\/mpimages\/208x308\/2TnB0TRT8k2-8FAHyLdbew.jpg","description":"In deze editie van Sports Woman de Thaise golf zusters Ariya en Moriya Jutanugarn. Garbi\u00f1e Muguruza heeft het talent om het vrouwentennis te beheersen, maar is ze consistent genoeg? Jade Jones streeft ernaar om de eerste drievoudig Olympisch kampioen in taekwondo te worden, terwijl Sarah Hendrickson's carri\u00e8re vol blessures haar hele sport ten goede kwam.","category":""}}