{"68575":{"channel":"280658496","start":"1669553700","end":"1669560900","title":"Burgos CF - Real Zaragoza","program_id":"1298797163","date":"","icon":"https:\/\/t-mobiletv.nl:443\/CPS\/images\/universal\/film\/program\/202211\/20221120\/36\/202211200900247099ot.jpg","description":"Verslag van de wedstrijd Burgos CF - Real Zaragoza, gespeeld in de Spaanse Segunda Divisi\u00f3n A.","category":""},"68625":{"channel":"280658496","start":"1669683300","end":"1669689300","title":"Burgos CF - Real Zaragoza","program_id":"1301030585","date":"","icon":"https:\/\/t-mobiletv.nl:443\/CPS\/images\/universal\/film\/program\/202211\/20221125\/48\/202211252100247315g8.jpg","description":"Verslag van de wedstrijd Burgos CF - Real Zaragoza, gespeeld in de Spaanse Segunda Divisi\u00f3n A.","category":""}}