{"42224":{"channel":"141430473","start":"1669152240","end":"1669158600","title":"Countdown To Christmas: A Christmas To Savour","program_id":"1296674602","date":"","icon":"https:\/\/t-mobiletv.nl:443\/CPS\/images\/universal\/film\/program\/202211\/20221115\/2\/202211150900405098gp.jpg","description":"Chef-kok Scarlett runt met haar beste vriendin een restaurant. Om inspiratie op te doen voor de feestdagen, wordt Scarlett naar een kookcursus gestuurd. Daar komt ze een oude rivaal tegen. Scarlett krijgt het ultieme kerstgevoel als er gevoelens tussen hen opbloeien.","category":""}}