{"51955":{"channel":"141430597","start":"1669544640","end":"1669545840","title":"Moonriders","program_id":"1299768311","date":"","icon":"https:\/\/t-mobiletv.nl:443\/CPS\/images\/universal\/film\/program\/202211\/20221122\/1\/20221122210115524jvd.jpg","description":"Mia's hoofd stroomt over van de creatieve idee\u00ebn. In haar kunstwerk wil ze graag haar Koreaanse roots verwerken. Aukje weet meteen aan wie ze Mia moet koppelen. Jaasir Linger is een kunstenaar die ook zijn brein niet af kan remmen. Hij werkt met veel verschillende materialen en verwerkt vaak zijn roots in zijn werk. Namelijk de Afro-Surinaamse religie van zijn voorouders, winti. Samen maken ze een kunstwerk op het toilet in museum De Pont waarin hun roots naar voren komen en representatie een grote rol speelt.","category":""}}