{"21197":{"channel":"tvwest","start":"1669676400","end":"1669678200","first":"N","idtitle":"NACHTPROGRAMMERING","title":"Nachtprogrammering","program_id":"C40BD9541F865FF838C70498EC36614B","date":"","icon":"https:\/\/images.nlziet.nl\/metadataimportimages\/source\/BB7DE9F9A4FCFA50DA44ED1C7EFC9E3BD78A1B3420928003124AB136C1F1A3D9.jpg","description":"Van 00.00 tot 07.00 uur doorlopende herhaling van de programmering van de voorafgaande avond.","category":""},"21199":{"channel":"tvwest","start":"1669678200","end":"1669701600","first":"N","idtitle":"NIETSISONMOGELIJK","title":"Niets is Onmogelijk","program_id":"045886B49E7507FF67050963602FF45B","date":"","icon":"https:\/\/images.nlziet.nl\/metadataimportimages\/source\/AA296DE8EFC8DA6DE50E9364223B2E1D5AF1583D6EC87FE290D8FE0DB315FDA9.jpg","description":"Uitzendingen van de UKGR (Universele kerk van Gods Rijk)","category":""},"21201":{"channel":"tvwest","start":"1669701600","end":"1669703400","first":"G","idtitle":"GROTEAMBITIES","title":"Grote Ambities","program_id":"F7DE9EB061D7E752E6B0D2477A09CA17","date":"","icon":"https:\/\/images.nlziet.nl\/metadataimportimages\/source\/8B28040677254D59C7B2A618A08D85279622599197393B397E04817382B04D1E.jpg","description":"In de zesdelige serie Grote Ambities volgt Omroep West mensen met een missie. Stuk voor stuk prachtige mensen, met passie voor hun ambitie.","category":""},"21202":{"channel":"tvwest","start":"1669703400","end":"1669704420","first":"T","idtitle":"TVWESTNIEUWS","title":"TV West Nieuws","program_id":"D9A78844AB0FCD15567A9A7BF2544F37","date":"","icon":"https:\/\/images.nlziet.nl\/metadataimportimages\/source\/CFD0B9CFA8C2626263A44B654F7F0E87370E4D88CD6F483B9A8C993C231B7D22.jpg","description":"Het TV West Nieuws brengt het laatste nieuws en achtergronden uit de regio Zuid-Holland Noord.","category":""},"21203":{"channel":"tvwest","start":"1669704420","end":"1669704600","first":"W","idtitle":"WEER","title":"Weer","program_id":"D90AD64DB3E3E05B7CB8B400B1095CF9","date":"","icon":"https:\/\/images.nlziet.nl\/metadataimportimages\/source\/33E358F62ED355F7CC213ADAD4C9B1463EE1986A67C59F3D2CA89E8D3A7FC8FC.jpg","description":"De weersverwachting van de regio Zuid-Holland-Noord met Huub Mizee of Jordi Bloem of Margot Ribberink.","category":""},"21204":{"channel":"tvwest","start":"1669704600","end":"1669705200","first":"R","idtitle":"REGIONED","title":"RegioNED","program_id":"5CAC634D4017C8EAD8F493632DDE962D","date":"","icon":"https:\/\/images.nlziet.nl\/metadataimportimages\/source\/9F5173FAFF0F5C5A609E9D484309B28E7F286A21015DD535A76AF57A65520BBD.jpg","description":"In RegioNED kunt u dagelijks kijken naar opmerkelijke verhalen uit de twaalf provincien. Verhalen over klein, menselijk nieuws. Nieuws dat te klein is voor welk ander programma dan ook.","category":""},"21205":{"channel":"tvwest","start":"1669705200","end":"1669707000","first":"G","idtitle":"GROTEAMBITIES","title":"Grote Ambities","program_id":"A7D144477EDFC6361CF5EDBE549839E5","date":"","icon":"https:\/\/images.nlziet.nl\/metadataimportimages\/source\/8B28040677254D59C7B2A618A08D85279622599197393B397E04817382B04D1E.jpg","description":"In de zesdelige serie Grote Ambities volgt Omroep West mensen met een missie. Stuk voor stuk prachtige mensen, met passie voor hun ambitie.","category":""},"21206":{"channel":"tvwest","start":"1669707000","end":"1669708020","first":"T","idtitle":"TVWESTNIEUWS","title":"TV West Nieuws","program_id":"9B6CE5D853F0795569ADD0FBD29C6C0A","date":"","icon":"https:\/\/images.nlziet.nl\/metadataimportimages\/source\/CFD0B9CFA8C2626263A44B654F7F0E87370E4D88CD6F483B9A8C993C231B7D22.jpg","description":"Het TV West Nieuws brengt het laatste nieuws en achtergronden uit de regio Zuid-Holland Noord.","category":""},"21207":{"channel":"tvwest","start":"1669708020","end":"1669708200","first":"W","idtitle":"WEER","title":"Weer","program_id":"39BC912126006F19553388A21710FA67","date":"","icon":"https:\/\/images.nlziet.nl\/metadataimportimages\/source\/33E358F62ED355F7CC213ADAD4C9B1463EE1986A67C59F3D2CA89E8D3A7FC8FC.jpg","description":"De weersverwachting van de regio Zuid-Holland-Noord met Huub Mizee of Jordi Bloem of Margot Ribberink.","category":""},"21208":{"channel":"tvwest","start":"1669708200","end":"1669708800","first":"R","idtitle":"REGIONED","title":"RegioNED","program_id":"918BCAB660E363CD1A362067FA26ABD9","date":"","icon":"https:\/\/images.nlziet.nl\/metadataimportimages\/source\/9F5173FAFF0F5C5A609E9D484309B28E7F286A21015DD535A76AF57A65520BBD.jpg","description":"In RegioNED kunt u dagelijks kijken naar opmerkelijke verhalen uit de twaalf provincien. Verhalen over klein, menselijk nieuws. Nieuws dat te klein is voor welk ander programma dan ook.","category":""},"21209":{"channel":"tvwest","start":"1669708800","end":"1669710600","first":"G","idtitle":"GROTEAMBITIES","title":"Grote Ambities","program_id":"99DE004EF94E781889CA12C8BA6C9AE7","date":"","icon":"https:\/\/images.nlziet.nl\/metadataimportimages\/source\/8B28040677254D59C7B2A618A08D85279622599197393B397E04817382B04D1E.jpg","description":"In de zesdelige serie Grote Ambities volgt Omroep West mensen met een missie. Stuk voor stuk prachtige mensen, met passie voor hun ambitie.","category":""},"21210":{"channel":"tvwest","start":"1669710600","end":"1669711620","first":"T","idtitle":"TVWESTNIEUWS","title":"TV West Nieuws","program_id":"5EC4EECB000A93CE03B947735518D287","date":"","icon":"https:\/\/images.nlziet.nl\/metadataimportimages\/source\/CFD0B9CFA8C2626263A44B654F7F0E87370E4D88CD6F483B9A8C993C231B7D22.jpg","description":"Het TV West Nieuws brengt het laatste nieuws en achtergronden uit de regio Zuid-Holland Noord.","category":""},"21211":{"channel":"tvwest","start":"1669711620","end":"1669711800","first":"W","idtitle":"WEER","title":"Weer","program_id":"B82DD530618AF77941F169887C83A7C5","date":"","icon":"https:\/\/images.nlziet.nl\/metadataimportimages\/source\/33E358F62ED355F7CC213ADAD4C9B1463EE1986A67C59F3D2CA89E8D3A7FC8FC.jpg","description":"De weersverwachting van de regio Zuid-Holland-Noord met Huub Mizee of Jordi Bloem of Margot Ribberink.","category":""},"21212":{"channel":"tvwest","start":"1669711800","end":"1669712400","first":"R","idtitle":"REGIONED","title":"RegioNED","program_id":"FA7B2A11F9DA9E86F1A0C71CF6C1C16B","date":"","icon":"https:\/\/images.nlziet.nl\/metadataimportimages\/source\/9F5173FAFF0F5C5A609E9D484309B28E7F286A21015DD535A76AF57A65520BBD.jpg","description":"In RegioNED kunt u dagelijks kijken naar opmerkelijke verhalen uit de twaalf provincien. Verhalen over klein, menselijk nieuws. Nieuws dat te klein is voor welk ander programma dan ook.","category":""},"21213":{"channel":"tvwest","start":"1669712400","end":"1669714200","first":"G","idtitle":"GROTEAMBITIES","title":"Grote Ambities","program_id":"5FB47BC22E95236A2F8099112C36FD16","date":"","icon":"https:\/\/images.nlziet.nl\/metadataimportimages\/source\/8B28040677254D59C7B2A618A08D85279622599197393B397E04817382B04D1E.jpg","description":"In de zesdelige serie Grote Ambities volgt Omroep West mensen met een missie. Stuk voor stuk prachtige mensen, met passie voor hun ambitie.","category":""},"21215":{"channel":"tvwest","start":"1669714200","end":"1669715220","first":"T","idtitle":"TVWESTNIEUWS","title":"TV West Nieuws","program_id":"B751D1CEB50999715EF02E5A18133B48","date":"","icon":"https:\/\/images.nlziet.nl\/metadataimportimages\/source\/CFD0B9CFA8C2626263A44B654F7F0E87370E4D88CD6F483B9A8C993C231B7D22.jpg","description":"Het TV West Nieuws brengt het laatste nieuws en achtergronden uit de regio Zuid-Holland Noord.","category":""},"21216":{"channel":"tvwest","start":"1669715220","end":"1669715400","first":"W","idtitle":"WEER","title":"Weer","program_id":"A8AA141B5DDD2D660568B26A8D336814","date":"","icon":"https:\/\/images.nlziet.nl\/metadataimportimages\/source\/33E358F62ED355F7CC213ADAD4C9B1463EE1986A67C59F3D2CA89E8D3A7FC8FC.jpg","description":"De weersverwachting van de regio Zuid-Holland-Noord met Huub Mizee of Jordi Bloem of Margot Ribberink.","category":""},"21217":{"channel":"tvwest","start":"1669715400","end":"1669716000","first":"R","idtitle":"REGIONED","title":"RegioNED","program_id":"3305647691D58BF4F135EED055075F4C","date":"","icon":"https:\/\/images.nlziet.nl\/metadataimportimages\/source\/9F5173FAFF0F5C5A609E9D484309B28E7F286A21015DD535A76AF57A65520BBD.jpg","description":"In RegioNED kunt u dagelijks kijken naar opmerkelijke verhalen uit de twaalf provincien. Verhalen over klein, menselijk nieuws. Nieuws dat te klein is voor welk ander programma dan ook.","category":""},"21218":{"channel":"tvwest","start":"1669716000","end":"1669717800","first":"G","idtitle":"GROTEAMBITIES","title":"Grote Ambities","program_id":"78D848A8BEB1E80CE84B31D87A7AD765","date":"","icon":"https:\/\/images.nlziet.nl\/metadataimportimages\/source\/8B28040677254D59C7B2A618A08D85279622599197393B397E04817382B04D1E.jpg","description":"In de zesdelige serie Grote Ambities volgt Omroep West mensen met een missie. Stuk voor stuk prachtige mensen, met passie voor hun ambitie.","category":""},"21219":{"channel":"tvwest","start":"1669717800","end":"1669718820","first":"T","idtitle":"TVWESTNIEUWS","title":"TV West Nieuws","program_id":"B1A7B20574487399B154BD873271BD2B","date":"","icon":"https:\/\/images.nlziet.nl\/metadataimportimages\/source\/CFD0B9CFA8C2626263A44B654F7F0E87370E4D88CD6F483B9A8C993C231B7D22.jpg","description":"Het TV West Nieuws brengt het laatste nieuws en achtergronden uit de regio Zuid-Holland Noord.","category":""},"21220":{"channel":"tvwest","start":"1669718820","end":"1669719000","first":"W","idtitle":"WEER","title":"Weer","program_id":"D575FCC58AFF1A9EA042F89E43A6A226","date":"","icon":"https:\/\/images.nlziet.nl\/metadataimportimages\/source\/33E358F62ED355F7CC213ADAD4C9B1463EE1986A67C59F3D2CA89E8D3A7FC8FC.jpg","description":"De weersverwachting van de regio Zuid-Holland-Noord met Huub Mizee of Jordi Bloem of Margot Ribberink.","category":""},"21221":{"channel":"tvwest","start":"1669719000","end":"1669719600","first":"R","idtitle":"REGIONED","title":"RegioNED","program_id":"9B76DB58631D7875E7F6E2DCBB1744A8","date":"","icon":"https:\/\/images.nlziet.nl\/metadataimportimages\/source\/9F5173FAFF0F5C5A609E9D484309B28E7F286A21015DD535A76AF57A65520BBD.jpg","description":"In RegioNED kunt u dagelijks kijken naar opmerkelijke verhalen uit de twaalf provincien. Verhalen over klein, menselijk nieuws. Nieuws dat te klein is voor welk ander programma dan ook.","category":""},"21222":{"channel":"tvwest","start":"1669719600","end":"1669720500","first":"N","idtitle":"NOSJOURNAAL","title":"NOS Journaal","program_id":"D30CD925CA3C176A3D9A47A81FC6CE8A","date":"","icon":"https:\/\/nlzietprodstorage.blob.core.windows.net\/","description":"Naast het landelijke nieuws in dit bulletin ook aandacht voor het belangrijkste nieuws van de regionale omroepen.","category":""},"21224":{"channel":"tvwest","start":"1669720500","end":"1669721400","first":"R","idtitle":"REGIONED","title":"RegioNED","program_id":"192DD12608ACEF0E6FA9F8E91BF949DE","date":"","icon":"https:\/\/images.nlziet.nl\/metadataimportimages\/source\/9F5173FAFF0F5C5A609E9D484309B28E7F286A21015DD535A76AF57A65520BBD.jpg","description":"In RegioNED kunt u dagelijks kijken naar opmerkelijke verhalen uit de twaalf provincien. Verhalen over klein, menselijk nieuws. Nieuws dat te klein is voor welk ander programma dan ook.","category":""},"21225":{"channel":"tvwest","start":"1669721400","end":"1669722420","first":"T","idtitle":"TVWESTNIEUWS","title":"TV West Nieuws","program_id":"A9BBF1D7BEAD7599F07DC36EF74347B9","date":"","icon":"https:\/\/images.nlziet.nl\/metadataimportimages\/source\/CFD0B9CFA8C2626263A44B654F7F0E87370E4D88CD6F483B9A8C993C231B7D22.jpg","description":"Het TV West Nieuws brengt het laatste nieuws en achtergronden uit de regio Zuid-Holland Noord.","category":""},"21227":{"channel":"tvwest","start":"1669722420","end":"1669722600","first":"W","idtitle":"WEER","title":"Weer","program_id":"1230696257113DD98836019609D3CE18","date":"","icon":"https:\/\/images.nlziet.nl\/metadataimportimages\/source\/33E358F62ED355F7CC213ADAD4C9B1463EE1986A67C59F3D2CA89E8D3A7FC8FC.jpg","description":"De weersverwachting van de regio Zuid-Holland-Noord met Huub Mizee of Jordi Bloem of Margot Ribberink.","category":""},"21228":{"channel":"tvwest","start":"1669722600","end":"1669723200","first":"R","idtitle":"REGIONED","title":"RegioNED","program_id":"FA1BEE940532F837BE8AA280A1F95873","date":"","icon":"https:\/\/images.nlziet.nl\/metadataimportimages\/source\/9F5173FAFF0F5C5A609E9D484309B28E7F286A21015DD535A76AF57A65520BBD.jpg","description":"In RegioNED kunt u dagelijks kijken naar opmerkelijke verhalen uit de twaalf provincien. Verhalen over klein, menselijk nieuws. Nieuws dat te klein is voor welk ander programma dan ook.","category":""},"21229":{"channel":"tvwest","start":"1669723200","end":"1669725000","first":"G","idtitle":"GROTEAMBITIES","title":"Grote Ambities","program_id":"CFCC432CDC4791D3A994B3B878FC7BC6","date":"","icon":"https:\/\/images.nlziet.nl\/metadataimportimages\/source\/8B28040677254D59C7B2A618A08D85279622599197393B397E04817382B04D1E.jpg","description":"In de zesdelige serie Grote Ambities volgt Omroep West mensen met een missie. Stuk voor stuk prachtige mensen, met passie voor hun ambitie.","category":""},"21230":{"channel":"tvwest","start":"1669725000","end":"1669726020","first":"T","idtitle":"TVWESTNIEUWS","title":"TV West Nieuws","program_id":"D27F1404E8EC748B2C9FF60C24CC540A","date":"","icon":"https:\/\/images.nlziet.nl\/metadataimportimages\/source\/CFD0B9CFA8C2626263A44B654F7F0E87370E4D88CD6F483B9A8C993C231B7D22.jpg","description":"Het TV West Nieuws brengt het laatste nieuws en achtergronden uit de regio Zuid-Holland Noord.","category":""},"21231":{"channel":"tvwest","start":"1669726020","end":"1669726200","first":"W","idtitle":"WEER","title":"Weer","program_id":"B15C9C0364E22E37A32901DD37053A9B","date":"","icon":"https:\/\/images.nlziet.nl\/metadataimportimages\/source\/33E358F62ED355F7CC213ADAD4C9B1463EE1986A67C59F3D2CA89E8D3A7FC8FC.jpg","description":"De weersverwachting van de regio Zuid-Holland-Noord met Huub Mizee of Jordi Bloem of Margot Ribberink.","category":""},"21233":{"channel":"tvwest","start":"1669726200","end":"1669726800","first":"R","idtitle":"REGIONED","title":"RegioNed","program_id":"281F81F696569CDBDD8045DD6C6D815F","date":"","icon":"https:\/\/images.nlziet.nl\/metadataimportimages\/source\/9F5173FAFF0F5C5A609E9D484309B28E7F286A21015DD535A76AF57A65520BBD.jpg","description":"In RegioNED kunt u dagelijks kijken naar opmerkelijke verhalen uit de twaalf provincien. Verhalen over klein, menselijk nieuws. Nieuws dat te klein is voor welk ander programma dan ook.","category":""},"21235":{"channel":"tvwest","start":"1669726800","end":"1669728600","first":"G","idtitle":"GROTEAMBITIES","title":"Grote Ambities","program_id":"33895F9A0FCD8D70213A24C70C6B39F3","date":"","icon":"https:\/\/images.nlziet.nl\/metadataimportimages\/source\/8B28040677254D59C7B2A618A08D85279622599197393B397E04817382B04D1E.jpg","description":"In de zesdelige serie Grote Ambities volgt Omroep West mensen met een missie. Stuk voor stuk prachtige mensen, met passie voor hun ambitie.","category":""},"21236":{"channel":"tvwest","start":"1669728600","end":"1669729620","first":"T","idtitle":"TVWESTNIEUWS","title":"TV West Nieuws","program_id":"342F44EC1D8ADE046B495C2301124598","date":"","icon":"https:\/\/images.nlziet.nl\/metadataimportimages\/source\/CFD0B9CFA8C2626263A44B654F7F0E87370E4D88CD6F483B9A8C993C231B7D22.jpg","description":"Het TV West Nieuws brengt het laatste nieuws en achtergronden uit de regio Zuid-Holland Noord.","category":""},"21237":{"channel":"tvwest","start":"1669729620","end":"1669729800","first":"W","idtitle":"WEER","title":"Weer","program_id":"38B30212695E8612D1FF010D46228435","date":"","icon":"https:\/\/images.nlziet.nl\/metadataimportimages\/source\/33E358F62ED355F7CC213ADAD4C9B1463EE1986A67C59F3D2CA89E8D3A7FC8FC.jpg","description":"De weersverwachting van de regio Zuid-Holland-Noord met Huub Mizee of Jordi Bloem of Margot Ribberink.","category":""},"21238":{"channel":"tvwest","start":"1669729800","end":"1669730400","first":"R","idtitle":"REGIONED","title":"RegioNED","program_id":"B4FE4331BB5DD0FC699F968A3D6D49E3","date":"","icon":"https:\/\/images.nlziet.nl\/metadataimportimages\/source\/9F5173FAFF0F5C5A609E9D484309B28E7F286A21015DD535A76AF57A65520BBD.jpg","description":"In RegioNED kunt u dagelijks kijken naar opmerkelijke verhalen uit de twaalf provincien. Verhalen over klein, menselijk nieuws. Nieuws dat te klein is voor welk ander programma dan ook.","category":""},"21239":{"channel":"tvwest","start":"1669730400","end":"1669731300","first":"N","idtitle":"NOSJOURNAAL","title":"NOS Journaal","program_id":"2358CCE3B0985998FCA01F77404B778D","date":"","icon":"https:\/\/nlzietprodstorage.blob.core.windows.net\/","description":"Naast het landelijke nieuws in dit bulletin ook aandacht voor het belangrijkste nieuws van de regionale omroepen.","category":""},"21241":{"channel":"tvwest","start":"1669731300","end":"1669732200","first":"R","idtitle":"REGIONED","title":"RegioNED","program_id":"521D9AF5C59425F2A448F600E43694FA","date":"","icon":"https:\/\/images.nlziet.nl\/metadataimportimages\/source\/9F5173FAFF0F5C5A609E9D484309B28E7F286A21015DD535A76AF57A65520BBD.jpg","description":"In RegioNED kunt u dagelijks kijken naar opmerkelijke verhalen uit de twaalf provincien. Verhalen over klein, menselijk nieuws. Nieuws dat te klein is voor welk ander programma dan ook.","category":""},"21242":{"channel":"tvwest","start":"1669732200","end":"1669733220","first":"T","idtitle":"TVWESTNIEUWS","title":"TV West Nieuws","program_id":"C926D4BFFEBEDADA3981C4E18D98846D","date":"","icon":"https:\/\/images.nlziet.nl\/metadataimportimages\/source\/CFD0B9CFA8C2626263A44B654F7F0E87370E4D88CD6F483B9A8C993C231B7D22.jpg","description":"Het TV West Nieuws brengt het laatste nieuws en achtergronden uit de regio Zuid-Holland Noord.","category":""},"21243":{"channel":"tvwest","start":"1669733220","end":"1669733400","first":"W","idtitle":"WEER","title":"Weer","program_id":"045F297EEB431D056DE0076892DA925B","date":"","icon":"https:\/\/images.nlziet.nl\/metadataimportimages\/source\/33E358F62ED355F7CC213ADAD4C9B1463EE1986A67C59F3D2CA89E8D3A7FC8FC.jpg","description":"De weersverwachting van de regio Zuid-Holland-Noord met Huub Mizee of Jordi Bloem of Margot Ribberink.","category":""},"21244":{"channel":"tvwest","start":"1669733400","end":"1669734000","first":"R","idtitle":"REGIONED","title":"RegioNED","program_id":"C2D2175F8EC0DA80E5BA16260C55D9BB","date":"","icon":"https:\/\/images.nlziet.nl\/metadataimportimages\/source\/9F5173FAFF0F5C5A609E9D484309B28E7F286A21015DD535A76AF57A65520BBD.jpg","description":"In RegioNED kunt u dagelijks kijken naar opmerkelijke verhalen uit de twaalf provincien. Verhalen over klein, menselijk nieuws. Nieuws dat te klein is voor welk ander programma dan ook.","category":""},"21245":{"channel":"tvwest","start":"1669734000","end":"1669735800","first":"G","idtitle":"GROTEAMBITIES","title":"Grote Ambities","program_id":"9C1D1FB712A3BC97CB6503BEFFBE0D6C","date":"","icon":"https:\/\/images.nlziet.nl\/metadataimportimages\/source\/8B28040677254D59C7B2A618A08D85279622599197393B397E04817382B04D1E.jpg","description":"In de zesdelige serie Grote Ambities volgt Omroep West mensen met een missie. Stuk voor stuk prachtige mensen, met passie voor hun ambitie.","category":""},"21246":{"channel":"tvwest","start":"1669735800","end":"1669736820","first":"T","idtitle":"TVWESTNIEUWS","title":"TV West Nieuws","program_id":"14C774235BFC27386AA544B6E7FCF0EA","date":"","icon":"https:\/\/images.nlziet.nl\/metadataimportimages\/source\/CFD0B9CFA8C2626263A44B654F7F0E87370E4D88CD6F483B9A8C993C231B7D22.jpg","description":"Het TV West Nieuws brengt het laatste nieuws en achtergronden uit de regio Zuid-Holland Noord.","category":""},"21247":{"channel":"tvwest","start":"1669736820","end":"1669737000","first":"W","idtitle":"WEER","title":"Weer","program_id":"972E7349446FFF68340929C19AE524AD","date":"","icon":"https:\/\/images.nlziet.nl\/metadataimportimages\/source\/33E358F62ED355F7CC213ADAD4C9B1463EE1986A67C59F3D2CA89E8D3A7FC8FC.jpg","description":"De weersverwachting van de regio Zuid-Holland-Noord met Huub Mizee of Jordi Bloem of Margot Ribberink.","category":""},"21248":{"channel":"tvwest","start":"1669737000","end":"1669737600","first":"R","idtitle":"REGIONED","title":"RegioNED","program_id":"1CE40F391BC6C5DA5DED5018F31B4B58","date":"","icon":"https:\/\/images.nlziet.nl\/metadataimportimages\/source\/9F5173FAFF0F5C5A609E9D484309B28E7F286A21015DD535A76AF57A65520BBD.jpg","description":"In RegioNED kunt u dagelijks kijken naar opmerkelijke verhalen uit de twaalf provincien. Verhalen over klein, menselijk nieuws. Nieuws dat te klein is voor welk ander programma dan ook.","category":""},"21249":{"channel":"tvwest","start":"1669737600","end":"1669738500","first":"T","idtitle":"TEAMWEST","title":"Team West","program_id":"C6DC2DCB1924C6C9250D02B975111CA6","date":"","icon":"https:\/\/images.nlziet.nl\/metadataimportimages\/source\/9E852F551EAB1DD123ADA5D83E07AD003632BAE3FFF3463CC1FCE8CC3A6FC01F.jpg","description":"In het opsporingsprogramma Team West vraagt de politie-eenheid Den Haag jouw hulp bij het oplossen van misdrijven. Het programma heeft dankzij de hulp van kijkers tot heel veel resultaten geleid.","category":""},"21250":{"channel":"tvwest","start":"1669738500","end":"1669739400","first":"E","idtitle":"ERNSTSONDERWATERWERELD","title":"Ernst's OnderWaterWereld","program_id":"FFED0FCA63E63944CDB4C2F95A638848","date":"","icon":"https:\/\/images.nlziet.nl\/metadataimportimages\/source\/B84B99BADCCB076CE77CF247DD562E9C8419D12864E1EC7C1A9B554F89521FA6.jpg","description":"Ernst is ecoloog bij een waterschap, het Hoogheemraadschap van Delfland. In zijn serie &amp;quot;Ernst's OnderWaterWereld&amp;quot; vertelt hij over het leven in, op en langs het water.","category":""},"21251":{"channel":"tvwest","start":"1669739400","end":"1669740480","first":"T","idtitle":"TVWESTNIEUWS","title":"TV West Nieuws","program_id":"7339188953CD6220E9D9904CB23261BD","date":"","icon":"https:\/\/images.nlziet.nl\/metadataimportimages\/source\/CFD0B9CFA8C2626263A44B654F7F0E87370E4D88CD6F483B9A8C993C231B7D22.jpg","description":"Het TV West Nieuws brengt het laatste nieuws en achtergronden uit de regio Zuid-Holland Noord.","category":""},"21252":{"channel":"tvwest","start":"1669740480","end":"1669740720","first":"W","idtitle":"WEER","title":"Weer","program_id":"5854CF27E840CF0CA489EB42CE6BC2D1","date":"","icon":"https:\/\/images.nlziet.nl\/metadataimportimages\/source\/33E358F62ED355F7CC213ADAD4C9B1463EE1986A67C59F3D2CA89E8D3A7FC8FC.jpg","description":"De weersverwachting van de regio Zuid-Holland-Noord met Huub Mizee of Jordi Bloem of Margot Ribberink.","category":""},"21253":{"channel":"tvwest","start":"1669740720","end":"1669741200","first":"R","idtitle":"REGIONED","title":"RegioNED","program_id":"A103F04E27A5BF3095E8F358D702E1A1","date":"","icon":"https:\/\/images.nlziet.nl\/metadataimportimages\/source\/9F5173FAFF0F5C5A609E9D484309B28E7F286A21015DD535A76AF57A65520BBD.jpg","description":"In RegioNED kunt u dagelijks kijken naar opmerkelijke verhalen uit de twaalf provincien. Verhalen over klein, menselijk nieuws. Nieuws dat te klein is voor welk ander programma dan ook.","category":""},"21254":{"channel":"tvwest","start":"1669741200","end":"1669742100","first":"T","idtitle":"TEAMWEST","title":"Team West","program_id":"3C4CA1CBF3020BC1784D7376356CEEE8","date":"","icon":"https:\/\/images.nlziet.nl\/metadataimportimages\/source\/9E852F551EAB1DD123ADA5D83E07AD003632BAE3FFF3463CC1FCE8CC3A6FC01F.jpg","description":"In het opsporingsprogramma Team West vraagt de politie-eenheid Den Haag jouw hulp bij het oplossen van misdrijven. Het programma heeft dankzij de hulp van kijkers tot heel veel resultaten geleid.","category":""},"21255":{"channel":"tvwest","start":"1669742100","end":"1669743000","first":"E","idtitle":"ERNSTSONDERWATERWERELD","title":"Ernst's OnderWaterWereld","program_id":"8A71A61F3EE670DEDC5FB20C73487244","date":"","icon":"https:\/\/images.nlziet.nl\/metadataimportimages\/source\/B84B99BADCCB076CE77CF247DD562E9C8419D12864E1EC7C1A9B554F89521FA6.jpg","description":"Ernst is ecoloog bij een waterschap, het Hoogheemraadschap van Delfland. In zijn serie &amp;quot;Ernst's OnderWaterWereld&amp;quot; vertelt hij over het leven in, op en langs het water.","category":""},"21256":{"channel":"tvwest","start":"1669743000","end":"1669744080","first":"T","idtitle":"TVWESTNIEUWS","title":"TV West Nieuws","program_id":"5C52D402703929DFA88EAC683A65F15A","date":"","icon":"https:\/\/images.nlziet.nl\/metadataimportimages\/source\/CFD0B9CFA8C2626263A44B654F7F0E87370E4D88CD6F483B9A8C993C231B7D22.jpg","description":"Het TV West Nieuws brengt het laatste nieuws en achtergronden uit de regio Zuid-Holland Noord.","category":""},"21257":{"channel":"tvwest","start":"1669744080","end":"1669744320","first":"W","idtitle":"WEER","title":"Weer","program_id":"46AD5153BC541005AA2F3D49E53A1FE9","date":"","icon":"https:\/\/images.nlziet.nl\/metadataimportimages\/source\/33E358F62ED355F7CC213ADAD4C9B1463EE1986A67C59F3D2CA89E8D3A7FC8FC.jpg","description":"De weersverwachting van de regio Zuid-Holland-Noord met Huub Mizee of Jordi Bloem of Margot Ribberink.","category":""},"21258":{"channel":"tvwest","start":"1669744320","end":"1669744800","first":"R","idtitle":"REGIONED","title":"RegioNED","program_id":"2545D0ABD87D0A67E3EED06BAC6F22DA","date":"","icon":"https:\/\/images.nlziet.nl\/metadataimportimages\/source\/9F5173FAFF0F5C5A609E9D484309B28E7F286A21015DD535A76AF57A65520BBD.jpg","description":"In RegioNED kunt u dagelijks kijken naar opmerkelijke verhalen uit de twaalf provincien. Verhalen over klein, menselijk nieuws. Nieuws dat te klein is voor welk ander programma dan ook.","category":""},"21259":{"channel":"tvwest","start":"1669744800","end":"1669745700","first":"T","idtitle":"TEAMWEST","title":"Team West","program_id":"2DAAEC03B481E332C8C53C946E5D6183","date":"","icon":"https:\/\/images.nlziet.nl\/metadataimportimages\/source\/9E852F551EAB1DD123ADA5D83E07AD003632BAE3FFF3463CC1FCE8CC3A6FC01F.jpg","description":"In het opsporingsprogramma Team West vraagt de politie-eenheid Den Haag jouw hulp bij het oplossen van misdrijven. Het programma heeft dankzij de hulp van kijkers tot heel veel resultaten geleid.","category":""},"21260":{"channel":"tvwest","start":"1669745700","end":"1669746600","first":"E","idtitle":"ERNSTSONDERWATERWERELD","title":"Ernst's OnderWaterWereld","program_id":"0BB9F22FE9662EC3802ADAA99BA33FAD","date":"","icon":"https:\/\/images.nlziet.nl\/metadataimportimages\/source\/B84B99BADCCB076CE77CF247DD562E9C8419D12864E1EC7C1A9B554F89521FA6.jpg","description":"Ernst is ecoloog bij een waterschap, het Hoogheemraadschap van Delfland. In zijn serie &amp;quot;Ernst's OnderWaterWereld&amp;quot; vertelt hij over het leven in, op en langs het water.","category":""},"21261":{"channel":"tvwest","start":"1669746600","end":"1669747680","first":"T","idtitle":"TVWESTNIEUWS","title":"TV West Nieuws","program_id":"1CEF60B99F148969AB88D473B0215A12","date":"","icon":"https:\/\/images.nlziet.nl\/metadataimportimages\/source\/CFD0B9CFA8C2626263A44B654F7F0E87370E4D88CD6F483B9A8C993C231B7D22.jpg","description":"Het TV West Nieuws brengt het laatste nieuws en achtergronden uit de regio Zuid-Holland Noord.","category":""},"21262":{"channel":"tvwest","start":"1669747680","end":"1669747920","first":"W","idtitle":"WEER","title":"Weer","program_id":"86DBA62644ADD41918DAF0EF045728AB","date":"","icon":"https:\/\/images.nlziet.nl\/metadataimportimages\/source\/33E358F62ED355F7CC213ADAD4C9B1463EE1986A67C59F3D2CA89E8D3A7FC8FC.jpg","description":"De weersverwachting van de regio Zuid-Holland-Noord met Huub Mizee of Jordi Bloem of Margot Ribberink.","category":""},"21263":{"channel":"tvwest","start":"1669747920","end":"1669748400","first":"R","idtitle":"REGIONED","title":"RegioNED","program_id":"B0A570CCE935E0C93C26F70CB44706B7","date":"","icon":"https:\/\/images.nlziet.nl\/metadataimportimages\/source\/9F5173FAFF0F5C5A609E9D484309B28E7F286A21015DD535A76AF57A65520BBD.jpg","description":"In RegioNED kunt u dagelijks kijken naar opmerkelijke verhalen uit de twaalf provincien. Verhalen over klein, menselijk nieuws. Nieuws dat te klein is voor welk ander programma dan ook.","category":""},"21264":{"channel":"tvwest","start":"1669748400","end":"1669750200","first":"N","idtitle":"NOSJOURNAAL","title":"NOS Journaal","program_id":"2A44D51DA5B01C5562DEF6994666BD55","date":"","icon":"https:\/\/images.nlziet.nl\/metadataimportimages\/source\/8E9E258F1ED0C1A2722054E42CD1E4A124279844A6FC29A8BA3C92418F97C4EF.jpg","description":"Naast het landelijke nieuws in dit bulletin ook aandacht voor het belangrijkste nieuws van de regionale omroepen.","category":""},"21266":{"channel":"tvwest","start":"1669750200","end":"1669751280","first":"T","idtitle":"TVWESTNIEUWS","title":"TV West Nieuws","program_id":"C8F7DE7FE48424A97134D2DC9C688674","date":"","icon":"https:\/\/images.nlziet.nl\/metadataimportimages\/source\/CFD0B9CFA8C2626263A44B654F7F0E87370E4D88CD6F483B9A8C993C231B7D22.jpg","description":"Het TV West Nieuws brengt het laatste nieuws en achtergronden uit de regio Zuid-Holland Noord.","category":""},"21267":{"channel":"tvwest","start":"1669751280","end":"1669751520","first":"W","idtitle":"WEER","title":"Weer","program_id":"941C58BC65E4056E6284F71A3A8CE8DC","date":"","icon":"https:\/\/images.nlziet.nl\/metadataimportimages\/source\/33E358F62ED355F7CC213ADAD4C9B1463EE1986A67C59F3D2CA89E8D3A7FC8FC.jpg","description":"De weersverwachting van de regio Zuid-Holland-Noord met Huub Mizee of Jordi Bloem of Margot Ribberink.","category":""},"21268":{"channel":"tvwest","start":"1669751520","end":"1669752000","first":"R","idtitle":"REGIONED","title":"RegioNED","program_id":"B7C017A906378CF3257F8F295725C1D1","date":"","icon":"https:\/\/images.nlziet.nl\/metadataimportimages\/source\/9F5173FAFF0F5C5A609E9D484309B28E7F286A21015DD535A76AF57A65520BBD.jpg","description":"In RegioNED kunt u dagelijks kijken naar opmerkelijke verhalen uit de twaalf provincien. Verhalen over klein, menselijk nieuws. Nieuws dat te klein is voor welk ander programma dan ook.","category":""},"21269":{"channel":"tvwest","start":"1669752000","end":"1669752900","first":"T","idtitle":"TEAMWEST","title":"Team West","program_id":"06D2608AC480984AAEF10E2D99D09FA6","date":"","icon":"https:\/\/images.nlziet.nl\/metadataimportimages\/source\/9E852F551EAB1DD123ADA5D83E07AD003632BAE3FFF3463CC1FCE8CC3A6FC01F.jpg","description":"In het opsporingsprogramma Team West vraagt de politie-eenheid Den Haag jouw hulp bij het oplossen van misdrijven. Het programma heeft dankzij de hulp van kijkers tot heel veel resultaten geleid.","category":""},"21270":{"channel":"tvwest","start":"1669752900","end":"1669753800","first":"E","idtitle":"ERNSTSONDERWATERWERELD","title":"Ernst's OnderWaterWereld","program_id":"11EA79139E3E8846B32724B5911BAF95","date":"","icon":"https:\/\/images.nlziet.nl\/metadataimportimages\/source\/B84B99BADCCB076CE77CF247DD562E9C8419D12864E1EC7C1A9B554F89521FA6.jpg","description":"Ernst is ecoloog bij een waterschap, het Hoogheemraadschap van Delfland. In zijn serie &amp;quot;Ernst's OnderWaterWereld&amp;quot; vertelt hij over het leven in, op en langs het water.","category":""},"21271":{"channel":"tvwest","start":"1669753800","end":"1669754880","first":"T","idtitle":"TVWESTNIEUWS","title":"TV West Nieuws","program_id":"EE8DC4F0DFC2E07B7C6525D80480D501","date":"","icon":"https:\/\/images.nlziet.nl\/metadataimportimages\/source\/CFD0B9CFA8C2626263A44B654F7F0E87370E4D88CD6F483B9A8C993C231B7D22.jpg","description":"Het TV West Nieuws brengt het laatste nieuws en achtergronden uit de regio Zuid-Holland Noord.","category":""},"21272":{"channel":"tvwest","start":"1669754880","end":"1669755120","first":"W","idtitle":"WEER","title":"Weer","program_id":"953F31203C5794064937412B6DFDE79E","date":"","icon":"https:\/\/images.nlziet.nl\/metadataimportimages\/source\/33E358F62ED355F7CC213ADAD4C9B1463EE1986A67C59F3D2CA89E8D3A7FC8FC.jpg","description":"De weersverwachting van de regio Zuid-Holland-Noord met Huub Mizee of Jordi Bloem of Margot Ribberink.","category":""},"21273":{"channel":"tvwest","start":"1669755120","end":"1669755600","first":"R","idtitle":"REGIONED","title":"RegioNED","program_id":"DD5D4218EEF104A71938E41E08990309","date":"","icon":"https:\/\/images.nlziet.nl\/metadataimportimages\/source\/9F5173FAFF0F5C5A609E9D484309B28E7F286A21015DD535A76AF57A65520BBD.jpg","description":"In RegioNED kunt u dagelijks kijken naar opmerkelijke verhalen uit de twaalf provincien. Verhalen over klein, menselijk nieuws. Nieuws dat te klein is voor welk ander programma dan ook.","category":""},"21274":{"channel":"tvwest","start":"1669755600","end":"1669756500","first":"T","idtitle":"TEAMWEST","title":"Team West","program_id":"3DBE2E1EBDB06FDBAFABB774C95D3C45","date":"","icon":"https:\/\/images.nlziet.nl\/metadataimportimages\/source\/9E852F551EAB1DD123ADA5D83E07AD003632BAE3FFF3463CC1FCE8CC3A6FC01F.jpg","description":"In het opsporingsprogramma Team West vraagt de politie-eenheid Den Haag jouw hulp bij het oplossen van misdrijven. Het programma heeft dankzij de hulp van kijkers tot heel veel resultaten geleid.","category":""},"21275":{"channel":"tvwest","start":"1669756500","end":"1669757400","first":"E","idtitle":"ERNSTSONDERWATERWERELD","title":"Ernst's OnderWaterWereld","program_id":"07CB192EF7A3EC27426F8D42867FD7D0","date":"","icon":"https:\/\/images.nlziet.nl\/metadataimportimages\/source\/B84B99BADCCB076CE77CF247DD562E9C8419D12864E1EC7C1A9B554F89521FA6.jpg","description":"Ernst is ecoloog bij een waterschap, het Hoogheemraadschap van Delfland. In zijn serie &amp;quot;Ernst's OnderWaterWereld&amp;quot; vertelt hij over het leven in, op en langs het water.","category":""},"21276":{"channel":"tvwest","start":"1669757400","end":"1669758480","first":"T","idtitle":"TVWESTNIEUWS","title":"TV West Nieuws","program_id":"B7704EFE51E2594AF8AB7B7F6C6D519A","date":"","icon":"https:\/\/images.nlziet.nl\/metadataimportimages\/source\/CFD0B9CFA8C2626263A44B654F7F0E87370E4D88CD6F483B9A8C993C231B7D22.jpg","description":"Het TV West Nieuws brengt het laatste nieuws en achtergronden uit de regio Zuid-Holland Noord.","category":""},"21277":{"channel":"tvwest","start":"1669758480","end":"1669758720","first":"W","idtitle":"WEER","title":"Weer","program_id":"910C8600EF167CD62458926CD1ADBE2E","date":"","icon":"https:\/\/images.nlziet.nl\/metadataimportimages\/source\/33E358F62ED355F7CC213ADAD4C9B1463EE1986A67C59F3D2CA89E8D3A7FC8FC.jpg","description":"De weersverwachting van de regio Zuid-Holland-Noord met Huub Mizee of Jordi Bloem of Margot Ribberink.","category":""},"21278":{"channel":"tvwest","start":"1669758720","end":"1669759200","first":"R","idtitle":"REGIONED","title":"RegioNED","program_id":"DB6DC61F1CFAF2CDCA5B00C849AD5116","date":"","icon":"https:\/\/images.nlziet.nl\/metadataimportimages\/source\/9F5173FAFF0F5C5A609E9D484309B28E7F286A21015DD535A76AF57A65520BBD.jpg","description":"In RegioNED kunt u dagelijks kijken naar opmerkelijke verhalen uit de twaalf provincien. Verhalen over klein, menselijk nieuws. Nieuws dat te klein is voor welk ander programma dan ook.","category":""},"21279":{"channel":"tvwest","start":"1669759200","end":"1669760100","first":"T","idtitle":"TEAMWEST","title":"Team West","program_id":"35E07C913FE0D98BC471A9DE50943BD8","date":"","icon":"https:\/\/images.nlziet.nl\/metadataimportimages\/source\/9E852F551EAB1DD123ADA5D83E07AD003632BAE3FFF3463CC1FCE8CC3A6FC01F.jpg","description":"In het opsporingsprogramma Team West vraagt de politie-eenheid Den Haag jouw hulp bij het oplossen van misdrijven. Het programma heeft dankzij de hulp van kijkers tot heel veel resultaten geleid.","category":""},"21280":{"channel":"tvwest","start":"1669760100","end":"1669761000","first":"E","idtitle":"ERNSTSONDERWATERWERELD","title":"Ernst's OnderWaterWereld","program_id":"1E65E9D048C206BEA267D1944F2D2FD8","date":"","icon":"https:\/\/images.nlziet.nl\/metadataimportimages\/source\/B84B99BADCCB076CE77CF247DD562E9C8419D12864E1EC7C1A9B554F89521FA6.jpg","description":"Ernst is ecoloog bij een waterschap, het Hoogheemraadschap van Delfland. In zijn serie &amp;quot;Ernst's OnderWaterWereld&amp;quot; vertelt hij over het leven in, op en langs het water.","category":""},"21281":{"channel":"tvwest","start":"1669761000","end":"1669762080","first":"T","idtitle":"TVWESTNIEUWS","title":"TV West Nieuws","program_id":"116EF8FC113FC585916E0D5DD6F35991","date":"","icon":"https:\/\/images.nlziet.nl\/metadataimportimages\/source\/CFD0B9CFA8C2626263A44B654F7F0E87370E4D88CD6F483B9A8C993C231B7D22.jpg","description":"Het TV West Nieuws brengt het laatste nieuws en achtergronden uit de regio Zuid-Holland Noord.","category":""},"21282":{"channel":"tvwest","start":"1669762080","end":"1669762320","first":"W","idtitle":"WEER","title":"Weer","program_id":"1C04B56EA73409DEB6D723BFEE85213C","date":"","icon":"https:\/\/images.nlziet.nl\/metadataimportimages\/source\/33E358F62ED355F7CC213ADAD4C9B1463EE1986A67C59F3D2CA89E8D3A7FC8FC.jpg","description":"De weersverwachting van de regio Zuid-Holland-Noord met Huub Mizee of Jordi Bloem of Margot Ribberink.","category":""},"21283":{"channel":"tvwest","start":"1669762320","end":"1669762800","first":"R","idtitle":"REGIONED","title":"RegioNED","program_id":"1F7C1B72193492E685FFFA4CB6D4E756","date":"","icon":"https:\/\/images.nlziet.nl\/metadataimportimages\/source\/9F5173FAFF0F5C5A609E9D484309B28E7F286A21015DD535A76AF57A65520BBD.jpg","description":"In RegioNED kunt u dagelijks kijken naar opmerkelijke verhalen uit de twaalf provincien. Verhalen over klein, menselijk nieuws. Nieuws dat te klein is voor welk ander programma dan ook.","category":""}}