{"6252":{"channel":"sbs9","start":"1669152739","end":"1669160555","title":"The Frighteners","program_id":"BED25B162A60EEB0B7C7E0541F77DDA2","date":"","icon":"https:\/\/images.nlziet.nl\/metadataimportimages\/source\/6BE57C1213C18CE80F2E8293D68CEAE403BFD72C8F04156FCD1C0230EBB84E12.jpg","description":"Frank Bannister heeft na een auto-ongeluk een gave gekregen. Hij kan namelijk geesten zien. Als er op bovennatuurlijke wijze mensen worden vermoord, is Bannister \u00e9\u00e9n van de hoofdverdachten.","category":""}}