{"1232":{"channel":"170","start":"1668828600","end":"1668830400","title":"Cross Talk","program_id":"899088414","date":"","icon":"https:\/\/images.tv.kpn.com\/epg\/9AS0MjqNvTgqeUo9Aj5qDL9AycbSco4vmUXlCQOuWpqzOU\/1920x1080.jpg?blurred=false","description":"Programma met Randy Weiss","category":""},"1255":{"channel":"170","start":"1668866400","end":"1668868200","title":"Cross Talk","program_id":"899088483","date":"","icon":"https:\/\/images.tv.kpn.com\/epg\/9AS0MjqNvTgqeUo9Aj5qDL9AycbSco4vmUXlCQOuWpqzOU\/1920x1080.jpg?blurred=false","description":"Programma met Randy Weiss","category":""},"7583":{"channel":"170","start":"1668979800","end":"1668981600","title":"Cross Talk","program_id":"899131854","date":"","icon":"https:\/\/images.tv.kpn.com\/epg\/9AS0MjqNvTgqeUo9Aj5qDL9AycbSco4vmUXlCQOuWpqzOU\/1920x1080.jpg?blurred=false","description":"Programma met Randy Weiss","category":""},"13826":{"channel":"170","start":"1669001400","end":"1669003200","title":"Cross Talk","program_id":"899173923","date":"","icon":"https:\/\/images.tv.kpn.com\/epg\/9AS0MjqNvTgqeUo9Aj5qDL9AycbSco4vmUXlCQOuWpqzOU\/1920x1080.jpg?blurred=false","description":"Programma met Randy Weiss","category":""},"13846":{"channel":"170","start":"1669037400","end":"1669039200","title":"Cross Talk","program_id":"899174040","date":"","icon":"https:\/\/images.tv.kpn.com\/epg\/9AS0MjqNvTgqeUo9Aj5qDL9AycbSco4vmUXlCQOuWpqzOU\/1920x1080.jpg?blurred=false","description":"Programma met Randy Weiss","category":""},"40107":{"channel":"170","start":"1669402800","end":"1669404600","title":"Cross Talk","program_id":"899360136","date":"","icon":"https:\/\/images.tv.kpn.com\/epg\/9AS0MjqNvTgqeUo9Aj5qDL9AycbSco4vmUXlCQOuWpqzOU\/1920x1080.jpg?blurred=false","description":"Programma met Randy Weiss","category":""},"46631":{"channel":"170","start":"1669433400","end":"1669435200","title":"Cross Talk","program_id":"899402613","date":"","icon":"https:\/\/images.tv.kpn.com\/epg\/9AS0MjqNvTgqeUo9Aj5qDL9AycbSco4vmUXlCQOuWpqzOU\/1920x1080.jpg?blurred=false","description":"Programma met Randy Weiss","category":""},"46652":{"channel":"170","start":"1669471200","end":"1669473000","title":"Cross Talk","program_id":"899402688","date":"","icon":"https:\/\/images.tv.kpn.com\/epg\/9AS0MjqNvTgqeUo9Aj5qDL9AycbSco4vmUXlCQOuWpqzOU\/1920x1080.jpg?blurred=false","description":"Programma met Randy Weiss","category":""},"52808":{"channel":"170","start":"1669584900","end":"1669586700","title":"Cross Talk","program_id":"899445345","date":"","icon":"https:\/\/images.tv.kpn.com\/epg\/9AS0MjqNvTgqeUo9Aj5qDL9AycbSco4vmUXlCQOuWpqzOU\/1920x1080.jpg?blurred=false","description":"Programma met Randy Weiss","category":""},"59070":{"channel":"170","start":"1669606260","end":"1669608000","title":"Cross Talk","program_id":"899486562","date":"","icon":"https:\/\/images.tv.kpn.com\/epg\/9AS0MjqNvTgqeUo9Aj5qDL9AycbSco4vmUXlCQOuWpqzOU\/1920x1080.jpg?blurred=false","description":"Programma met Randy Weiss","category":""},"59090":{"channel":"170","start":"1669642200","end":"1669644000","title":"Cross Talk","program_id":"899486673","date":"","icon":"https:\/\/images.tv.kpn.com\/epg\/9AS0MjqNvTgqeUo9Aj5qDL9AycbSco4vmUXlCQOuWpqzOU\/1920x1080.jpg?blurred=false","description":"Programma met Randy Weiss","category":""},"85111":{"channel":"170","start":"1670007600","end":"1670009400","title":"Cross Talk","program_id":"899666892","date":"","icon":"https:\/\/images.tv.kpn.com\/epg\/9AS0MjqNvTgqeUo9Aj5qDL9AycbSco4vmUXlCQOuWpqzOU\/1920x1080.jpg?blurred=false","description":"Programma met Randy Weiss","category":""},"91217":{"channel":"170","start":"1670038200","end":"1670040000","title":"Cross Talk","program_id":"899709357","date":"","icon":"https:\/\/images.tv.kpn.com\/epg\/9AS0MjqNvTgqeUo9Aj5qDL9AycbSco4vmUXlCQOuWpqzOU\/1920x1080.jpg?blurred=false","description":"Programma met Randy Weiss","category":""},"91238":{"channel":"170","start":"1670076000","end":"1670077800","title":"Cross Talk","program_id":"899709474","date":"","icon":"https:\/\/images.tv.kpn.com\/epg\/9AS0MjqNvTgqeUo9Aj5qDL9AycbSco4vmUXlCQOuWpqzOU\/1920x1080.jpg?blurred=false","description":"Programma met Randy Weiss","category":""}}