{"92930":{"channel":"24","start":"1670020500","end":"1670027700","title":"Species II","program_id":"899650059","date":"","icon":"https:\/\/images.tv.kpn.com\/epg\/BoaFM4lhhyfZ9BHOONjESE0CUvKKi9BjCbn3i759BJuMO0\/1920x1080.jpg?blurred=false","description":"De eerste bemande vlucht naar Mars is een feit. Tijdens deze reis raakt astronaut Patrick Ross besmet met buitenaards DNA. Ross heeft daardoor een onbedwingbare drang om te paren. De vrouwen met wie hij het bed deelt, overlijden terwijl ze bevallen van een alien. Wetenschappers moeten voorkomen dat Ross meer nakomelingen produceert. Ze zetten een vrouw met buitenaards DNA, Eve, in om hem op te sporen. Ross en zijn nazaten moeten worden gedood, voordat zij de mensheid vernietigen.","category":""}}